invent/__about__.py
invent/__init__.py
invent/app.py
invent/datastore.py
invent/i18n.py
invent/media.py
invent/page.py
invent/pubsub.py
invent/utils.py
invent/ui/__init__.py
invent/ui/core.py
invent/ui/utils.py
invent/ui/widgets/__init__.py
invent/ui/widgets/button.py
invent/ui/widgets/image.py
invent/ui/widgets/old_button.py
invent/ui/widgets/textbox.py
invent/ui/widgets/textinput.py
invent-0.0.1a2.dist-info/METADATA
invent-0.0.1a2.dist-info/WHEEL
invent-0.0.1a2.dist-info/licenses/AUTHORS
invent-0.0.1a2.dist-info/licenses/LICENSE
invent-0.0.1a2.dist-info/RECORD
