Metadata-Version: 2.1
Name: invent
Version: 0.0.1a2
Summary: Invent - an app framework for beginner programmers
Project-URL: Homepage, https://github.com/invent-framework/invent
Project-URL: Bug Tracker, https://github.com/invent-framework/invent/issues
Author-email: "Nicholas H.Tollervey" <ntoll@ntoll.org>
License-File: AUTHORS
License-File: LICENSE
Classifier: Development Status :: 3 - Alpha
Classifier: Environment :: WebAssembly :: Emscripten
Classifier: Intended Audience :: Developers
Classifier: Intended Audience :: Education
Classifier: Intended Audience :: End Users/Desktop
Classifier: License :: OSI Approved :: Apache Software License
Classifier: Natural Language :: English
Classifier: Operating System :: Android
Classifier: Operating System :: MacOS
Classifier: Operating System :: Microsoft :: Windows :: Windows 10
Classifier: Operating System :: POSIX :: Linux
Classifier: Operating System :: iOS
Classifier: Programming Language :: Python :: 3 :: Only
Classifier: Topic :: Education
Classifier: Topic :: Software Development
Classifier: Topic :: Software Development :: Libraries :: Application Frameworks
Classifier: Topic :: Software Development :: User Interfaces
Classifier: Topic :: System :: Software Distribution
Requires-Python: >=3.7
